sphinx_cjkspace/__init__.py
sphinx_cjkspace/cjkspace.py
sphinx_cjkspace/utils.py
sphinx_cjkspace-0.1.3.dist-info/LICENSE
sphinx_cjkspace-0.1.3.dist-info/METADATA
sphinx_cjkspace-0.1.3.dist-info/WHEEL
sphinx_cjkspace-0.1.3.dist-info/top_level.txt
sphinx_cjkspace-0.1.3.dist-info/RECORD
