Metadata-Version: 2.1
Name: sphinx-cjkspace
Version: 0.1.3
Summary: Python extension to remove extra spaces between CJK characters
Home-page: https://github.com/seisman/sphinx-cjkspace
Author: Dongdong Tian
Author-email: seisman.info@gmail.com
License: The MIT License (MIT)
Requires-Dist: sphinx
Requires-Dist: zhon
